noop/__init__.py
kernelai-0.0.0.dist-info/LICENSE
kernelai-0.0.0.dist-info/METADATA
kernelai-0.0.0.dist-info/WHEEL
kernelai-0.0.0.dist-info/top_level.txt
kernelai-0.0.0.dist-info/RECORD
