Metadata-Version: 2.1
Name: kernelai
Version: 0.0.0
Summary: AI Kernel
Author: Patryk Zdunowski
Author-email: zdunekere@gmail.com
Classifier: Programming Language :: Python :: 3
Classifier: License :: OSI Approved :: MIT License
Classifier: Operating System :: OS Independent
Requires-Python: >=3.6
License-File: LICENSE
